README.rst
setup.py
pandas_timeseries.egg-info/PKG-INFO
pandas_timeseries.egg-info/SOURCES.txt
pandas_timeseries.egg-info/dependency_links.txt
pandas_timeseries.egg-info/not-zip-safe
pandas_timeseries.egg-info/requires.txt
pandas_timeseries.egg-info/top_level.txt
timeseries/__init__.py
timeseries/timeseries.py